my_package/__init__.py
mycommand/__init__.py
mycommand/__main__.py
mycommand/cli.py
mycommand_tool-0.1.1.dist-info/licenses/LICENSE
mycommand_tool-0.1.1.dist-info/METADATA
mycommand_tool-0.1.1.dist-info/WHEEL
mycommand_tool-0.1.1.dist-info/entry_points.txt
mycommand_tool-0.1.1.dist-info/top_level.txt
mycommand_tool-0.1.1.dist-info/RECORD
